acad_sdk/__init__.py
acad_sdk/cli.py
acad_sdk/client.py
camp_codegen-2.0.0.dist-info/METADATA
camp_codegen-2.0.0.dist-info/WHEEL
camp_codegen-2.0.0.dist-info/entry_points.txt
camp_codegen-2.0.0.dist-info/top_level.txt
camp_codegen-2.0.0.dist-info/RECORD
