Metadata-Version: 2.4
Name: camp-codegen
Version: 2.0.0
Summary: Camp Codegen: Python SDK and colorful CLI for AI-assisted smart contract generation, compilation, and deployment
Author-email: BlockX AI International <mohit@blockxint.com>
License: MIT
Project-URL: Homepage, https://blockxint.com
Project-URL: API, https://acadcodegen-production.up.railway.app
Project-URL: Source, https://blockxint.com
Keywords: blockchain,solidity,deployment,ai,sdk
Classifier: Programming Language :: Python :: 3
Classifier: License :: OSI Approved :: MIT License
Classifier: Operating System :: OS Independent
Classifier: Topic :: Software Development :: Libraries
Classifier: Topic :: Utilities
Requires-Python: >=3.9
Requires-Dist: requests>=2.31.0
Requires-Dist: rich>=13.7.0
